AdsbAnomalyDetector/AdsbAnomalyDetector.py
AdsbAnomalyDetector/AdsbAnomalyDetector2.py
AdsbAnomalyDetector/B_Model_AbstractModel.py
AdsbAnomalyDetector/B_Model_AircraftClassification.py
AdsbAnomalyDetector/B_Model_AircraftClassification_Utils.py
AdsbAnomalyDetector/B_Model_FloodingSolver.py
AdsbAnomalyDetector/B_Model_InterpolationDetector.py
AdsbAnomalyDetector/B_Model_ReplaySolver.py
AdsbAnomalyDetector/B_Model_ReplaySolver_Utils_hashing.py
AdsbAnomalyDetector/B_Model_TrajectorySeparator.py
AdsbAnomalyDetector/B_Model_Utils_DyT.py
AdsbAnomalyDetector/B_Model_Utils_MulAttention.py
AdsbAnomalyDetector/B_Model_Utils_TF_Modules.py
AdsbAnomalyDetector/C_Constants_AircraftClassification.py
AdsbAnomalyDetector/C_Constants_AircraftClassification_DefaultCTX.py
AdsbAnomalyDetector/C_Constants_FloodingSolver.py
AdsbAnomalyDetector/C_Constants_FloodingSolver_DefaultCTX.py
AdsbAnomalyDetector/C_Constants_InterpolationDetector.py
AdsbAnomalyDetector/C_Constants_InterpolationDetector_DefaultCTX.py
AdsbAnomalyDetector/C_Constants_ReplaySolver.py
AdsbAnomalyDetector/C_Constants_ReplaySolver_DefaultCTX.py
AdsbAnomalyDetector/C_Constants_TrajectorySeparator.py
AdsbAnomalyDetector/C_Constants_TrajectorySeparator_DefaultCTX.py
AdsbAnomalyDetector/D_DataLoader_AbstractDataLoader.py
AdsbAnomalyDetector/D_DataLoader_AircraftClassification_DataLoader.py
AdsbAnomalyDetector/D_DataLoader_AircraftClassification_Utils.py
AdsbAnomalyDetector/D_DataLoader_Airports.py
AdsbAnomalyDetector/D_DataLoader_FloodingSolver_DataLoader.py
AdsbAnomalyDetector/D_DataLoader_FloodingSolver_Utils.py
AdsbAnomalyDetector/D_DataLoader_InterpolationDetector_DataLoader.py
AdsbAnomalyDetector/D_DataLoader_InterpolationDetector_Utils.py
AdsbAnomalyDetector/D_DataLoader_ReplaySolver_DataLoader.py
AdsbAnomalyDetector/D_DataLoader_ReplaySolver_Utils.py
AdsbAnomalyDetector/D_DataLoader_TrajectorySeparator_DataLoader.py
AdsbAnomalyDetector/D_DataLoader_TrajectorySeparator_Utils.py
adsbanomalydetector-0.9.dist-info/METADATA
adsbanomalydetector-0.9.dist-info/WHEEL
adsbanomalydetector-0.9.dist-info/top_level.txt
adsbanomalydetector-0.9.dist-info/RECORD
