Metadata-Version: 2.4
Name: AdsbAnomalyDetector
Version: 0.9
Summary: Low altitude aircraft anomaly detector
Author: Pirolley Melvyn
Author-email: 
Keywords: python,deep learning,tensorflow,aircraft,classification,ADS-B
Classifier: Intended Audience :: Education
Classifier: Programming Language :: Python :: 3
Classifier: Operating System :: MacOS :: MacOS X
Classifier: Operating System :: Microsoft :: Windows
Requires-Dist: tensorflow
Requires-Dist: numpy
Requires-Dist: pandas
Requires-Dist: scikit-learn
Requires-Dist: matplotlib
Requires-Dist: pickle-mixin
Requires-Dist: cartopy
Requires-Dist: numpy_typing
Requires-Dist: flask
Requires-Dist: flask-cors
Dynamic: author
Dynamic: classifier
Dynamic: description
Dynamic: description-content-type
Dynamic: keywords
Dynamic: requires-dist
Dynamic: summary
